helptool/__init__.py
helptool-1.0.2.dist-info/METADATA
helptool-1.0.2.dist-info/WHEEL
helptool-1.0.2.dist-info/top_level.txt
helptool-1.0.2.dist-info/RECORD
